Metadata-Version: 2.1
Name: jk-keyvaluestore
Version: 0.2019.9.17.1
Summary: This python module implements a simple key-value data base based on JSON data stored in a directory.
Home-page: https://github.com/jkpubsrc/python-module-jk-keyvaluestore
Author: Jürgen Knauth
Author-email: pubsrc@binary-overflow.de
License: Apache 2.0
Download-URL: https://github.com/jkpubsrc/python-module-jk-keyvaluestore/tarball/0.2019.9.17.1
Keywords: kvp,json
Platform: UNKNOWN
Classifier: Programming Language :: Python :: 3
Classifier: Development Status :: 4 - Beta
Classifier: License :: OSI Approved :: Apache Software License
